MANIFEST.in
README.rst
setup.py
CGvsPhoto/__init__.py
CGvsPhoto/baseline_histograms.py
CGvsPhoto/construct_DB.py
CGvsPhoto/file_link_shuffler.py
CGvsPhoto/image_loader.py
CGvsPhoto/model.py
CGvsPhoto.egg-info/PKG-INFO
CGvsPhoto.egg-info/SOURCES.txt
CGvsPhoto.egg-info/dependency_links.txt
CGvsPhoto.egg-info/not-zip-safe
CGvsPhoto.egg-info/requires.txt
CGvsPhoto.egg-info/top_level.txt