Metadata-Version: 1.0
Name: CGvsPhoto
Version: 0.0.3
Summary: A deep-learning method for distinguishing computer graphics from real photogrphic images
Home-page: https://github.com/NicoRahm/CGvsPhoto
Author: Nicolas Rahmouni
Author-email: nicolas.rahmouni@polytechnique.edu
License: MIT
Platform: UNKNOWN
